README.rst
setup.cfg
setup.py
memeapi/__init__.py
memeapi/_compat.py
memeapi/api.py
memeapi/exceptions.py
memeapi.egg-info/PKG-INFO
memeapi.egg-info/SOURCES.txt
memeapi.egg-info/dependency_links.txt
memeapi.egg-info/not-zip-safe
memeapi.egg-info/requires.txt
memeapi.egg-info/top_level.txt