Metadata-Version: 1.1
Name: memeapi
Version: 0.2.3
Summary: Tiny wrapper over memegenerator.net API.
Home-page: https://github.com/surrealists/memeapi
Author: Cristian Cabrera
Author-email: surrealcristian@gmail.com
License: MIT
Platform: UNKNOWN
Classifier: Development Status :: 1 - Planning
Classifier: Intended Audience :: Developers
Classifier: License :: OSI Approved :: MIT License
Classifier: Natural Language :: English
Classifier: Programming Language :: Python
